PyTujian/__init__.py
PyTujian/__main__.py
PyTujian/api.py
PyTujian/cmd.py
PyTujian/tujian.py
PyTujian/utils.py
PyTujian-0.1.25.dist-info/LICENSE
PyTujian-0.1.25.dist-info/METADATA
PyTujian-0.1.25.dist-info/WHEEL
PyTujian-0.1.25.dist-info/entry_points.txt
PyTujian-0.1.25.dist-info/top_level.txt
PyTujian-0.1.25.dist-info/RECORD
