Metadata-Version: 2.1
Name: PyTujian
Version: 0.1.25
Summary: A simlpe tool for Tujian
Home-page: https://github.com/gggxbbb/tujian_python
Author: gggxbbb
Author-email: gamegxb@163.com
License: UNKNOWN
Platform: UNKNOWN
Classifier: Programming Language :: Python :: 3
Classifier: License :: OSI Approved :: MIT License
Classifier: Operating System :: OS Independent
Requires-Python: >=3.5
License-File: LICENSE
Requires-Dist: pytz (>=2021.1)
Requires-Dist: tqdm (>=4.61.2)
Requires-Dist: requests (>=2.26.0)
